odoo/addons/mail_tracking_mailgun/README.rst
odoo/addons/mail_tracking_mailgun/__init__.py
odoo/addons/mail_tracking_mailgun/__manifest__.py
odoo/addons/mail_tracking_mailgun/i18n/am.po
odoo/addons/mail_tracking_mailgun/i18n/ar.po
odoo/addons/mail_tracking_mailgun/i18n/bg.po
odoo/addons/mail_tracking_mailgun/i18n/bs.po
odoo/addons/mail_tracking_mailgun/i18n/ca.po
odoo/addons/mail_tracking_mailgun/i18n/cs.po
odoo/addons/mail_tracking_mailgun/i18n/da.po
odoo/addons/mail_tracking_mailgun/i18n/de.po
odoo/addons/mail_tracking_mailgun/i18n/el_GR.po
odoo/addons/mail_tracking_mailgun/i18n/en_GB.po
odoo/addons/mail_tracking_mailgun/i18n/es.po
odoo/addons/mail_tracking_mailgun/i18n/es_CR.po
odoo/addons/mail_tracking_mailgun/i18n/es_EC.po
odoo/addons/mail_tracking_mailgun/i18n/es_MX.po
odoo/addons/mail_tracking_mailgun/i18n/es_VE.po
odoo/addons/mail_tracking_mailgun/i18n/et.po
odoo/addons/mail_tracking_mailgun/i18n/eu.po
odoo/addons/mail_tracking_mailgun/i18n/fi.po
odoo/addons/mail_tracking_mailgun/i18n/fr.po
odoo/addons/mail_tracking_mailgun/i18n/fr_CA.po
odoo/addons/mail_tracking_mailgun/i18n/fr_CH.po
odoo/addons/mail_tracking_mailgun/i18n/gl.po
odoo/addons/mail_tracking_mailgun/i18n/hr.po
odoo/addons/mail_tracking_mailgun/i18n/hr_HR.po
odoo/addons/mail_tracking_mailgun/i18n/hu.po
odoo/addons/mail_tracking_mailgun/i18n/it.po
odoo/addons/mail_tracking_mailgun/i18n/ja.po
odoo/addons/mail_tracking_mailgun/i18n/lt.po
odoo/addons/mail_tracking_mailgun/i18n/lv.po
odoo/addons/mail_tracking_mailgun/i18n/mail_tracking_mailgun.pot
odoo/addons/mail_tracking_mailgun/i18n/mk.po
odoo/addons/mail_tracking_mailgun/i18n/mn.po
odoo/addons/mail_tracking_mailgun/i18n/nb.po
odoo/addons/mail_tracking_mailgun/i18n/nb_NO.po
odoo/addons/mail_tracking_mailgun/i18n/nl.po
odoo/addons/mail_tracking_mailgun/i18n/nl_BE.po
odoo/addons/mail_tracking_mailgun/i18n/nl_NL.po
odoo/addons/mail_tracking_mailgun/i18n/pl.po
odoo/addons/mail_tracking_mailgun/i18n/pt.po
odoo/addons/mail_tracking_mailgun/i18n/pt_BR.po
odoo11_addon_mail_tracking_mailgun-11.0.1.2.1.dist-info/METADATA
odoo11_addon_mail_tracking_mailgun-11.0.1.2.1.dist-info/WHEEL
odoo11_addon_mail_tracking_mailgun-11.0.1.2.1.dist-info/top_level.txt
odoo11_addon_mail_tracking_mailgun-11.0.1.2.1.dist-info/RECORD
